sbo_service/__init__.py
sbo_service/service.py
sbo_service/__pycache__/__init__.cpython-310.pyc
sbo_service/__pycache__/service.cpython-310.pyc
sbo_service_layer-0.1.8.dist-info/LICENSE
sbo_service_layer-0.1.8.dist-info/METADATA
sbo_service_layer-0.1.8.dist-info/WHEEL
sbo_service_layer-0.1.8.dist-info/top_level.txt
sbo_service_layer-0.1.8.dist-info/RECORD
